django_sparkle_external-0.4.dist-info/DESCRIPTION.rst
django_sparkle_external-0.4.dist-info/METADATA
django_sparkle_external-0.4.dist-info/RECORD
django_sparkle_external-0.4.dist-info/WHEEL
django_sparkle_external-0.4.dist-info/metadata.json
django_sparkle_external-0.4.dist-info/top_level.txt
sparkle/__init__.py
sparkle/admin.py
sparkle/conf.py
sparkle/urls.py
sparkle/views.py
sparkle/__pycache__/__init__.cpython-34.pyc
sparkle/__pycache__/admin.cpython-34.pyc
sparkle/__pycache__/conf.cpython-34.pyc
sparkle/__pycache__/models.cpython-34.pyc
sparkle/__pycache__/urls.cpython-34.pyc
sparkle/__pycache__/views.cpython-34.pyc
sparkle/forms/__init__.py
sparkle/forms/__init__.pyc
sparkle/forms/widgets.py
sparkle/forms/widgets.pyc
sparkle/forms/__pycache__/__init__.cpython-34.pyc
sparkle/forms/__pycache__/widgets.cpython-34.pyc
sparkle/migrations/0001_initial.py
sparkle/migrations/0002_auto_20140701_1935.py
sparkle/migrations/0003_auto_20150411_1644.py
sparkle/migrations/__init__.py
sparkle/migrations/__pycache__/0001_initial.cpython-34.pyc
sparkle/migrations/__pycache__/0002_auto_20140701_0959.cpython-34.pyc
sparkle/migrations/__pycache__/0002_auto_20140701_1935.cpython-34.pyc
sparkle/migrations/__pycache__/__init__.cpython-34.pyc
sparkle/models/__init__.py
sparkle/models/base.py
sparkle/models/compat.py
sparkle/models/managers.py
sparkle/models/query.py
sparkle/models/__pycache__/__init__.cpython-34.pyc
sparkle/models/__pycache__/base.cpython-34.pyc
sparkle/models/__pycache__/compat.cpython-34.pyc
sparkle/models/__pycache__/managers.cpython-34.pyc
sparkle/models/__pycache__/query.cpython-34.pyc
sparkle/templates/sparkle/appcast.xml
sparkle/templates/sparkle/includes/ghostdown_editor.html
