Metadata-Version: 2.0
Name: django-sparkle-external
Version: 0.4
Summary: Django-sparkle is a Django application to make it easy to publish updates for your mac application using sparkle (intended for Django >= 1.5)
Home-page: https://github.com/shezi/django-sparkle-1.5
Author: Jason Emerick, Johannes Spielmann
Author-email: jemerick@gmail.com, jps@shezi.de
License: BSD
Platform: UNKNOWN
Classifier: Environment :: Web Environment
Classifier: Framework :: Django
Classifier: Intended Audience :: Developers
Classifier: License :: OSI Approved :: BSD License
Classifier: Operating System :: OS Independent
Classifier: Programming Language :: Python
Classifier: Topic :: Internet :: WWW/HTTP
Requires-Dist: django-absolute
Requires-Dist: django-ghostdown (>=0.3.1)
